cleanerPandasVol/__init__.py
cleanerPandasVol/categorical_encoder.py
cleanerPandasVol/data_type_converter.py
cleanerPandasVol/date_time_handler.py
cleanerPandasVol/feature_engineer.py
cleanerPandasVol/missing_value_handler.py
cleanerPandasVol/outlier_handler.py
cleanerPandasVol/scaler.py
cleanerPandasVol/text_cleaner.py
test/__init__.py
cleanerPandasVol-0.2.3.dist-info/LICENSE
cleanerPandasVol-0.2.3.dist-info/METADATA
cleanerPandasVol-0.2.3.dist-info/WHEEL
cleanerPandasVol-0.2.3.dist-info/top_level.txt
cleanerPandasVol-0.2.3.dist-info/RECORD
